fsms/patternmealy.v
module patternmealy(reset,clk,in,out);
input in,clk,reset;
output reg out=1'b0;
reg[1:0]current,next;
parameter A=2'd0,B=2'd1,C=2'd2,D=2'd3;
always@(*)begin
    case(current)
    A: next<=in?B:A;
    B: next<=in?B:C;
    C: next<=in?D:A;
    D: next<=in?B:A;
    endcase
end
always@(posedge clk)begin
    if(reset)
    current<=A;
    else
    current<=next;
end
always@(posedge clk)begin
    out<=((current==D)&&(in==1'b0));
end
endmodule

fsms/patternmealytb.v
`timescale 1ns/1ns
`include "patternmealy.v"
module patternmealytb;
reg clk;
reg in,reset;
wire out;
patternmealy dut(reset,clk,in,out);
initial begin
    clk=1'b0;
    reset=1'b1;
    #60 reset=1'b0;
    forever
    #55 clk=~clk;
end
initial begin
    $dumpfile("patternmealytb.vcd");
    $dumpvars(0,patternmealytb);
    $monitor($time," Input=%b,reset=%b,output=%b",in,reset,out);
    #80 in=1'b1;
    #100 in=1'b0;
    #120 in=1'b1;
    #100 in=1'b0;
    #75 in=1'b1;
    #75 $finish;
end
endmodule

fsms/patternmealytb.vcd
$date
	Wed Oct 18 16:10:14 2023
$end
$version
	Icarus Verilog
$end
$timescale
	1ns
$end
$scope module patternmealytb $end
$var wire 1 ! out $end
$var reg 1 " clk $end
$var reg 1 # in $end
$var reg 1 $ reset $end
$scope module dut $end
$var wire 1 " clk $end
$var wire 1 # in $end
$var wire 1 $ reset $end
$var parameter 2 % A $end
$var parameter 2 & B $end
$var parameter 2 ' C $end
$var parameter 2 ( D $end
$var reg 2 ) current [1:0] $end
$var reg 2 * next [1:0] $end
$var reg 1 ! out $end
$upscope $end
$upscope $end
$enddefinitions $end
$comment Show the parameter values. $end
$dumpall
b11 (
b10 '
b1 &
b0 %
$end
#0
$dumpvars
bx *
bx )
1$
x#
0"
0!
$end
#60
0$
#80
1#
#115
1"
#170
0"
#180
0#
#225
1"
#280
0"
#300
1#
#335
1"
#390
0"
#400
0#
1!
#445
1"
#475
1#
#500
0"
#510
0!
