fsms/patternmoore.v
module patternmoore(reset,clk,in,out);
input in,clk,reset;
output reg out;
reg[3:0]current,next;

parameter A=4'd0,B=4'd1,C=4'd2,D=4'd3,E=4'd4;
always@(*)begin
    case(current)
    A: next<=in?B:A;
    B: next<=in?B:C;
    C: next<=in?D:A;
    D: next<=in?B:E;
    E: next<=in?B:A;
    endcase
end
always@(posedge clk)begin
    current<=next;
end
always @(posedge clk ) begin
    out<=(current==E)? 1'b1:1'b0;
end
endmodule

fsms/patternmooretb.v
`timescale 1ns/1ns
`include "patternmoore.v"
module patternmooretb;
reg clk;
reg in,reset;
wire out;
patternmoore dut(reset,clk,in,out);
initial begin
    clk=1'b0;
    reset=1'b1;
    #60 reset=1'b0;
    forever
    #55 clk=~clk;
end
initial begin
    $dumpfile("patternmooretb.vcd");
    $dumpvars(0,patternmooretb);
    $monitor($time," Input=%b,reset=%b,output=%b",in,reset,out);
    #80 in=1'b1;
    #100 in=1'b0;
    #120 in=1'b1;
    #100 in=1'b0;
    #75 in=1'b1;
    #75 $finish;
end
endmodule

fsms/patternmooretb.vcd
$date
	Wed Oct 18 16:25:47 2023
$end
$version
	Icarus Verilog
$end
$timescale
	1ns
$end
$scope module patternmooretb $end
$var wire 1 ! out $end
$var reg 1 " clk $end
$var reg 1 # in $end
$var reg 1 $ reset $end
$scope module dut $end
$var wire 1 " clk $end
$var wire 1 # in $end
$var wire 1 $ reset $end
$var parameter 4 % A $end
$var parameter 4 & B $end
$var parameter 4 ' C $end
$var parameter 4 ( D $end
$var parameter 4 ) E $end
$var reg 4 * current [3:0] $end
$var reg 4 + next [3:0] $end
$var reg 1 ! out $end
$upscope $end
$upscope $end
$enddefinitions $end
$comment Show the parameter values. $end
$dumpall
b100 )
b11 (
b10 '
b1 &
b0 %
$end
#0
$dumpvars
bx +
bx *
1$
x#
0"
x!
$end
#60
0$
#80
1#
#115
1"
#170
0"
#180
0#
#225
1"
#280
0"
#300
1#
#335
1"
#390
0"
#400
0#
1!
#445
1"
#475
1#
#500
0"
#510
0!
