seqlogic/srff.v
module srff(s,r,q,qbar,clk);
input s,r;
output q,qbar;
input clk;
assign qbar=~q;
reg q;
always @(posedge clk ) 
begin
    if(s==1'b0 && r==1'b0)
    q<=q;
    else if(s==1'b0 && r==1'b1)
    q<=1'b0;
    else if(s==1'b1 && r==1'b0)
    q<=1'b1;
    else if(s==1'b1 && r==1'b1)
    q<=1'bx;
end
endmodule

seqlogic/srfftb.v
`include "srff.v"
`timescale 1ns/1ns
module srfftb;
reg s,r,clk;
wire qbar;
wire q;
srff DUT(s,r,q,qbar,clk);
initial begin
    clk=1'b0;
    forever
    #5 clk=~clk;
end
initial begin
    $dumpfile("srfftb.vcd");
    $dumpvars(0,srfftb);
    $monitor($time,"  S= %b, R=%b,Q = %b, Qbar = %b",s,r,q,qbar);
    #5 s=1'b0;r=1'b0;
    #10 s=1'b0;r=1'b1;
    #15 s=1'b0;r=1'b0;
    #20 s=1'b1;r=1'b0;
    #25 s=1'b0;r=1'b0;
    #30 s=1'b1;r=1'b1;
    $finish;
end
endmodule

seqlogic/srfftb.vcd
$date
	Thu Jun 22 21:26:08 2023
$end
$version
	Icarus Verilog
$end
$timescale
	1ns
$end
$scope module srfftb $end
$var wire 1 ! qbar $end
$var wire 1 " q $end
$var reg 1 # clk $end
$var reg 1 $ r $end
$var reg 1 % s $end
$scope module DUT $end
$var wire 1 # clk $end
$var wire 1 ! qbar $end
$var wire 1 $ r $end
$var wire 1 % s $end
$var reg 1 " q $end
$upscope $end
$upscope $end
$enddefinitions $end
$comment Show the parameter values. $end
$dumpall
$end
#0
$dumpvars
x%
x$
0#
x"
x!
$end
#5
0$
0%
1#
#10
0#
#15
1!
0"
1#
1$
#20
0#
#25
1#
#30
0#
0$
#35
1#
#40
0#
#45
1#
#50
0#
1%
#55
0!
1"
1#
#60
0#
#65
1#
#70
0#
#75
1#
0%
#80
0#
#85
1#
#90
0#
#95
1#
#100
0#
#105
x!
x"
1#
1$
1%
