seqlogic/tff.v
module tff(t,q,qbar,clk,rst);
input t,clk,rst;
output reg q;
output qbar;
assign qbar=~q;
always @(posedge clk or negedge rst ) begin
    if(rst)
    q<=1'b0;
    else
    begin
        if(t==1'b0)
        q<=q;
        else if(t==1'b1)
        q<=~q;
    end
end
endmodule

seqlogic/tfftb.v
`include "tff.v"
`timescale 1ns/1ns
module tfftb;
reg t,clk,rst;
wire q,qbar;
tff DUT(t,q,qbar,clk,rst);
initial begin
    clk=1'b0;
    forever
    #5 clk=~clk;
end
initial begin
    rst=1'b1;
    #10 rst=1'b0;
end
initial begin
    $dumpfile("tfftb.vcd");
    $dumpvars(0,tfftb);
    $monitor($time," T=%b, Q=%b ,Qbar=%b",t,q,qbar);
    #5  t=1'b0;
    #10 t=1'b1;
    #15 t=1'b0;
    #20 t=1'b1;
    #25 t=1'b0;
    #30 t=1'b1;
    #35 t=1'b0;
    $finish;
end
endmodule

seqlogic/tfftb.vcd
$date
	Fri Jun 23 00:23:39 2023
$end
$version
	Icarus Verilog
$end
$timescale
	1ns
$end
$scope module tfftb $end
$var wire 1 ! qbar $end
$var wire 1 " q $end
$var reg 1 # clk $end
$var reg 1 $ rst $end
$var reg 1 % t $end
$scope module DUT $end
$var wire 1 # clk $end
$var wire 1 ! qbar $end
$var wire 1 $ rst $end
$var wire 1 % t $end
$var reg 1 " q $end
$upscope $end
$upscope $end
$enddefinitions $end
$comment Show the parameter values. $end
$dumpall
$end
#0
$dumpvars
x%
1$
0#
x"
x!
$end
#5
1!
0"
0%
1#
#10
0#
0$
#15
0!
1"
1#
1%
#20
0#
#25
1!
0"
1#
#30
0#
0%
#35
1#
#40
0#
#45
1#
#50
0#
1%
#55
0!
1"
1#
#60
0#
#65
1!
0"
1#
#70
0#
#75
1#
0%
#80
0#
#85
1#
#90
0#
#95
1#
#100
0#
#105
0!
1"
1#
1%
#110
0#
#115
1!
0"
1#
#120
0#
#125
0!
1"
1#
#130
0#
#135
1!
0"
1#
#140
0#
0%
