comblogic/priority.v
module priority_encoder_4X2 (
    input wire [3:0] inputs, // 4 input lines
    output wire [1:0] out // 2-bit binary output
);

reg [1:0] encoded_output;

always @* begin
    casex(inputs)
        4'b0000: encoded_output = 2'bxx; 
        4'b1xxx: encoded_output = 2'b11; 
        4'b01xx: encoded_output = 2'b10; 
        4'b001x: encoded_output = 2'b01; 
        4'b0001: encoded_output = 2'b00; 
    endcase
end

assign out = encoded_output;

endmodule

comblogic/prioritytb.v
`include "priority.v"
`timescale 1ps/1ps
module tb();

  // Declare signals for the testbench
  reg [3:0] inputs;
  wire [1:0] out;

  priority_encoder_4X2 uut (
    .inputs(inputs),
    .out(out)
  );

  initial begin
    $dumpfile("dump.vcd");
    $dumpvars;

    inputs = 4'b0000; 
    #10;
    inputs = 4'b1000; 
    #10;
    inputs = 4'b0100; 
    #10;
    inputs = 4'b0010; 
    #10;
    inputs = 4'b0001; 
    #10;
    inputs = 4'b1100; 
    #10
    inputs = 4'b0110; 
    #10
    inputs = 4'b1111; 
    #10
    $finish;
  end
endmodule

comblogic/dump.vcd
$date
	Mon Sep 18 18:38:36 2023
$end
$version
	Icarus Verilog
$end
$timescale
	1ps
$end
$scope module tb $end
$var wire 2 ! out [1:0] $end
$var reg 4 " inputs [3:0] $end
$scope module uut $end
$var wire 4 # inputs [3:0] $end
$var wire 2 $ out [1:0] $end
$var reg 2 % encoded_output [1:0] $end
$upscope $end
$upscope $end
$enddefinitions $end
$comment Show the parameter values. $end
$dumpall
$end
#0
$dumpvars
bx %
bx $
b0 #
b0 "
bx !
$end
#10
b11 !
b11 $
b11 %
b1000 "
b1000 #
#20
b10 !
b10 $
b10 %
b100 "
b100 #
#30
b1 !
b1 $
b1 %
b10 "
b10 #
#40
b0 !
b0 $
b0 %
b1 "
b1 #
#50
b11 !
b11 $
b11 %
b1100 "
b1100 #
#60
b10 !
b10 $
b10 %
b110 "
b110 #
#70
b11 !
b11 $
b11 %
b1111 "
b1111 #
