counters/fbitgray.v
module grayc(clk,rst,out);
input clk,rst;
reg[3:0] count;
output reg[3:0] out;
always @(posedge clk or posedge rst ) begin
    if(rst)
    begin
    out<=4'h0;
    count<=4'h0;
    end
    else
    begin
    count<=count+1'b1;
    out<={(count[3]),(count[3]^count[2]),(count[2]^count[1]),(count[1]^count[0])};
    end

end
endmodule

counters/fbitgraytb.v
`include "fbitgray.v"
`timescale 1ns/1ns
module fbitgraytb;
reg clk,rst;
wire[3:0] out;
grayc DUT(clk,rst,out);
always #5 clk=~clk;
initial begin
    clk=1'b0;
    rst=1'b1;
    #2 rst=1'b0;
end
initial begin
    $dumpfile("fbitgraytb.vcd");
    $dumpvars(0,fbitgraytb);
    $monitor($time ," Clk=%b Reset=%b Output = %b",clk,rst,out);
    #200 $finish;
end
endmodule

counters/fbitgraytb.vcd
$date
	Sat Jul 01 23:23:41 2023
$end
$version
	Icarus Verilog
$end
$timescale
	1ns
$end
$scope module fbitgraytb $end
$var wire 4 ! out [3:0] $end
$var reg 1 " clk $end
$var reg 1 # rst $end
$scope module DUT $end
$var wire 1 " clk $end
$var wire 1 # rst $end
$var reg 4 $ count [3:0] $end
$var reg 4 % out [3:0] $end
$upscope $end
$upscope $end
$enddefinitions $end
$comment Show the parameter values. $end
$dumpall
$end
#0
$dumpvars
b0 %
b0 $
1#
0"
b0 !
$end
#2
0#
#5
b1 $
1"
#10
0"
#15
b1 !
b1 %
b10 $
1"
#20
0"
#25
b11 !
b11 %
b11 $
1"
#30
0"
#35
b10 !
b10 %
b100 $
1"
#40
0"
#45
b110 !
b110 %
b101 $
1"
#50
0"
#55
b111 !
b111 %
b110 $
1"
#60
0"
#65
b101 !
b101 %
b111 $
1"
#70
0"
#75
b100 !
b100 %
b1000 $
1"
#80
0"
#85
b1100 !
b1100 %
b1001 $
1"
#90
0"
#95
b1101 !
b1101 %
b1010 $
1"
#100
0"
#105
b1111 !
b1111 %
b1011 $
1"
#110
0"
#115
b1110 !
b1110 %
b1100 $
1"
#120
0"
#125
b1010 !
b1010 %
b1101 $
1"
#130
0"
#135
b1011 !
b1011 %
b1110 $
1"
#140
0"
#145
b1001 !
b1001 %
b1111 $
1"
#150
0"
#155
b1000 !
b1000 %
b0 $
1"
#160
0"
#165
b0 !
b0 %
b1 $
1"
#170
0"
#175
b1 !
b1 %
b10 $
1"
#180
0"
#185
b11 !
b11 %
b11 $
1"
#190
0"
#195
b10 !
b10 %
b100 $
1"
