counters/fbitripstr.v
module tflipflop(q,clk,reset);
input clk,reset;
output reg q;
always @(negedge clk) begin
    if(reset)
    q<=1'b0;
    else
    q<=(~q);
end
endmodule

module fbitrip(q,clk,reset);
input clk,reset;
output [3:0]q;
tflipflop t0(q[0],clk,reset);
tflipflop t1(q[1],q[0],reset);
tflipflop t2(q[2],q[1],reset);
tflipflop t3(q[3],q[2],reset);
endmodule

counters/fbitripstrtb.v
`include "fbitripstr.v"
`timescale 1ns/1ns
module fbitripstrtb;
reg clk,reset;
wire[3:0]q;
fbitrip DUT(q,clk,reset);
initial begin
    clk=1'b0;
    forever
    #5 clk=~clk;
end
initial begin
    reset=1'b1;
    #2 reset=1'b0;
end
initial begin
    $dumpfile("fbitripstrtb.vcd");
    $dumpvars(0,fbitripstrtb);
    $monitor($time, " Q=%h",q);
    #320 $finish;
end
endmodule

counters/fbitripstrtb.vcd
$date
	Sat Jul 01 00:40:43 2023
$end
$version
	Icarus Verilog
$end
$timescale
	1ns
$end
$scope module fbitripstrtb $end
$var wire 4 ! q [3:0] $end
$var reg 1 " clk $end
$var reg 1 # reset $end
$scope module DUT $end
$var wire 1 " clk $end
$var wire 1 # reset $end
$var wire 4 $ q [3:0] $end
$scope module t0 $end
$var wire 1 " clk $end
$var wire 1 # reset $end
$var reg 1 % q $end
$upscope $end
$scope module t1 $end
$var wire 1 & clk $end
$var wire 1 # reset $end
$var reg 1 ' q $end
$upscope $end
$scope module t2 $end
$var wire 1 ( clk $end
$var wire 1 # reset $end
$var reg 1 ) q $end
$upscope $end
$scope module t3 $end
$var wire 1 * clk $end
$var wire 1 # reset $end
$var reg 1 + q $end
$upscope $end
$upscope $end
$upscope $end
$enddefinitions $end
$comment Show the parameter values. $end
$dumpall
$end
#0
$dumpvars
0+
0*
0)
0(
0'
0&
0%
b0 $
1#
0"
b0 !
$end
#2
0#
#5
1"
#10
1&
b1 !
b1 $
1%
0"
#15
1"
#20
1(
1'
0&
b10 !
b10 $
0%
0"
#25
1"
#30
1&
b11 !
b11 $
1%
0"
#35
1"
#40
1*
1)
0(
0'
0&
b100 !
b100 $
0%
0"
#45
1"
#50
1&
b101 !
b101 $
1%
0"
#55
1"
#60
1(
1'
0&
b110 !
b110 $
0%
0"
#65
1"
#70
1&
b111 !
b111 $
1%
0"
#75
1"
#80
1+
0*
0)
0(
0'
0&
b1000 !
b1000 $
0%
0"
#85
1"
#90
1&
b1001 !
b1001 $
1%
0"
#95
1"
#100
1(
1'
0&
b1010 !
b1010 $
0%
0"
#105
1"
#110
1&
b1011 !
b1011 $
1%
0"
#115
1"
#120
1*
1)
0(
0'
0&
b1100 !
b1100 $
0%
0"
#125
1"
#130
1&
b1101 !
b1101 $
1%
0"
#135
1"
#140
1(
1'
0&
b1110 !
b1110 $
0%
0"
#145
1"
#150
1&
b1111 !
b1111 $
1%
0"
#155
1"
#160
0+
0*
0)
0(
0'
0&
b0 !
b0 $
0%
0"
#165
1"
#170
1&
b1 !
b1 $
1%
0"
#175
1"
#180
1(
1'
0&
b10 !
b10 $
0%
0"
#185
1"
#190
1&
b11 !
b11 $
1%
0"
#195
1"
#200
1*
1)
0(
0'
0&
b100 !
b100 $
0%
0"
#205
1"
#210
1&
b101 !
b101 $
1%
0"
#215
1"
#220
1(
1'
0&
b110 !
b110 $
0%
0"
#225
1"
#230
1&
b111 !
b111 $
1%
0"
#235
1"
#240
1+
0*
0)
0(
0'
0&
b1000 !
b1000 $
0%
0"
#245
1"
#250
1&
b1001 !
b1001 $
1%
0"
#255
1"
#260
1(
1'
0&
b1010 !
b1010 $
0%
0"
#265
1"
#270
1&
b1011 !
b1011 $
1%
0"
#275
1"
#280
1*
1)
0(
0'
0&
b1100 !
b1100 $
0%
0"
#285
1"
#290
1&
b1101 !
b1101 $
1%
0"
#295
1"
#300
1(
1'
0&
b1110 !
b1110 $
0%
0"
#305
1"
#310
1&
b1111 !
b1111 $
1%
0"
#315
1"
#320
0+
0*
0)
0(
0'
0&
b0 !
b0 $
0%
0"
