counters/fbitsyncud.v
module updown(clk,rst,enable,load,upordown,data_in,count);
input clk,rst,load,enable,upordown;
input[3:0] data_in;
output reg[3:0]count;
always @(posedge clk or posedge rst ) begin
    if(rst)
    count<=4'h0;
    else if(enable)begin
        if(load)
        count<=data_in;
        else begin
            if(upordown)
            count<=count+1'b1;
            else
            count<=count-1'b1;
        end
    end
end
endmodule

counters/fbitsyncudtb.v
`include "fbitsyncud.v"
`timescale 1ns/1ns
module fbitsyncudtb;
reg clk,rst,enable,upordown,load;
reg[3:0]data_in;
wire[3:0]q;
updown DUT(.clk(clk),.rst(rst),.count(q),.upordown(upordown),.enable(enable),.data_in(data_in),.load(load));
always #5 clk=~clk;
initial begin//initializeing values
    clk=1'b0;
    rst=1'b1;
    enable=1'b0;
    load=1'b0;
    data_in=4'b000;
end
initial begin
    $dumpfile("fbitsyncudtb.vcd");
    $dumpvars(0,fbitsyncudtb);
    $monitor($time," Clk=%b, Reset=%b, Enable=%b,Load=%b Updown = %b Data_in=%b Count=%b",clk,rst,enable,load,upordown,data_in,q);
    #5 rst=1'b0; //reset removed
    #5 enable=1'b1;//enabling the counter 
    upordown=1'b1;//upcounting

    #50 enable=1'b0;// disabling the counter

    #5 rst=1'b1;//resetting the counter to zero and removing it to show asynchronous operation
    #25 rst=1'b0;

    #10 enable=1'b1;//enabling the counter back and loading it with 1010 and enabling downcount
    #5 load=1'b1;
    upordown=1'b0;
    data_in=4'b1010;

    #5 load=1'b0;//removing load and enable downcount
    #20 upordown=1'b1;
    #50 enable=1'b0;//disable the counter finally

    #50 $finish;
end
endmodule

counters/fbitsyncudtb.vcd
$date
	Tue Jan 16 17:52:55 2024
$end
$version
	Icarus Verilog
$end
$timescale
	1ns
$end
$scope module fbitsyncudtb $end
$var wire 4 ! q [3:0] $end
$var reg 1 " clk $end
$var reg 4 # data_in [3:0] $end
$var reg 1 $ enable $end
$var reg 1 % load $end
$var reg 1 & rst $end
$var reg 1 ' upordown $end
$scope module DUT $end
$var wire 1 " clk $end
$var wire 4 ( data_in [3:0] $end
$var wire 1 $ enable $end
$var wire 1 % load $end
$var wire 1 & rst $end
$var wire 1 ' upordown $end
$var reg 4 ) count [3:0] $end
$upscope $end
$upscope $end
$enddefinitions $end
$comment Show the parameter values. $end
$dumpall
$end
#0
$dumpvars
b0 )
b0 (
x'
1&
0%
0$
b0 #
0"
b0 !
$end
#5
0&
1"
#10
1'
1$
0"
#15
b1 !
b1 )
1"
#20
0"
#25
b10 !
b10 )
1"
#30
0"
#35
b11 !
b11 )
1"
#40
0"
#45
b100 !
b100 )
1"
#50
0"
#55
b101 !
b101 )
1"
#60
0"
0$
#65
b0 !
b0 )
1"
1&
#70
0"
#75
1"
#80
0"
#85
1"
#90
0"
0&
#95
1"
#100
0"
1$
#105
b1010 !
b1010 )
1"
b1010 #
b1010 (
0'
1%
#110
0"
0%
#115
b1001 !
b1001 )
1"
#120
0"
#125
b1000 !
b1000 )
1"
#130
0"
1'
#135
b1001 !
b1001 )
1"
#140
0"
#145
b1010 !
b1010 )
1"
#150
0"
#155
b1011 !
b1011 )
1"
#160
0"
#165
b1100 !
b1100 )
1"
#170
0"
#175
b1101 !
b1101 )
1"
#180
0"
0$
