counters/johnsonc.v
module johnsonc(clk,rst,out);
input clk,rst;
output reg[3:0] out;
always @(posedge clk or posedge rst ) begin
    if(rst)
    out<=4'b0000;
    else
    out<={(~out[0]),out[3],out[2],out[1]};
end
endmodule

counters/johnsontb.v
`include "johnsonc.v"
`timescale 1ns/1ns
module johnsonctb;
reg clk,rst;
wire[3:0]out;
johnsonc DUT(clk,rst,out);
always #5 clk=~clk;
initial begin
    clk=1'b0;
    rst=1'b1;
    #2 rst=1'b0;
end
initial begin
    $dumpfile("johnsonctb.vcd");
    $dumpvars(0,johnsonctb);
    $monitor($time," Clk=%b Reset = %b Output = %b ",clk,rst,out);
    #200  $finish;
end
endmodule

counters/johnsonctb.vcd
$date
	Sat Jul 01 23:45:54 2023
$end
$version
	Icarus Verilog
$end
$timescale
	1ns
$end
$scope module johnsonctb $end
$var wire 4 ! out [3:0] $end
$var reg 1 " clk $end
$var reg 1 # rst $end
$scope module DUT $end
$var wire 1 " clk $end
$var wire 1 # rst $end
$var reg 4 $ out [3:0] $end
$upscope $end
$upscope $end
$enddefinitions $end
$comment Show the parameter values. $end
$dumpall
$end
#0
$dumpvars
b1000 $
1#
0"
b1000 !
$end
#2
0#
#5
b1100 !
b1100 $
1"
#10
0"
#15
b1110 !
b1110 $
1"
#20
0"
#25
b1111 !
b1111 $
1"
#30
0"
#35
b111 !
b111 $
1"
#40
0"
#45
b11 !
b11 $
1"
#50
0"
#55
b1 !
b1 $
1"
#60
0"
#65
b0 !
b0 $
1"
#70
0"
#75
b1000 !
b1000 $
1"
#80
0"
#85
b1100 !
b1100 $
1"
#90
0"
#95
b1110 !
b1110 $
1"
#100
0"
#105
b1111 !
b1111 $
1"
#110
0"
#115
b111 !
b111 $
1"
#120
0"
#125
b11 !
b11 $
1"
#130
0"
#135
b1 !
b1 $
1"
#140
0"
#145
b0 !
b0 $
1"
#150
0"
#155
b1000 !
b1000 $
1"
#160
0"
#165
b1100 !
b1100 $
1"
#170
0"
#175
b1110 !
b1110 $
1"
#180
0"
#185
b1111 !
b1111 $
1"
#190
0"
#195
b111 !
b111 $
1"
